lab5/e16267_lab5_part2/reg_file.v
// Computer Architecture (CO224) - Lab 05
// Design: Register File of Simple Processor
// Author: E/16/267

module reg_file(IN, OUT1, OUT2, INADDRESS, OUT1ADDRESS, OUT2ADDRESS, WRITE, CLK, RESET);

//reg_file myregfile(WRITEDATA, REGOUT1, REGOUT2, WRITEREG, READREG1, READREG2, WRITEENABLE, CLK, RESET);

	input CLK,WRITE,RESET;
	input [2:0] INADDRESS,OUT1ADDRESS, OUT2ADDRESS;
	input [7:0] IN;
	output [7:0] OUT1, OUT2;
	
	reg [7:0] r[7:0]; //for assign to 7 registers
	integer i;

	assign #2 OUT1=r[OUT1ADDRESS];
	assign #2 OUT2=r[OUT2ADDRESS];
	
	//for reset=1 with level trigerring
	always @(RESET) 	
	begin
		if(RESET)
		#2   //timing delay
			for (i=0; i<8; i=i+1)   //making registers array
			begin
                r[i]=8'b00000000; 
			end
	end
	
	//for no reset && write with edge triggering
	always @(posedge CLK)
	begin
		if(!RESET && WRITE)
			begin
				#2 r[INADDRESS]=IN;  //assign writedata to registers
			end
	end
	
	
	
endmodule

lab5/e16267_lab5_part2/reg_tb.v
// Computer Architecture (CO224) - Lab 05
// Design: Register File Testbench of Simple Processor
// Author: E/16/167


module reg_tb;
    
    reg [7:0] WRITEDATA;
    reg [2:0] WRITEREG, READREG1, READREG2;
    reg CLK, RESET, WRITEENABLE; 
    wire [7:0] REGOUT1, REGOUT2;
    
    reg_file myregfile(WRITEDATA, REGOUT1, REGOUT2, WRITEREG, READREG1, READREG2, WRITEENABLE, CLK, RESET);
       
    initial
    begin
        CLK = 1'b1;
        
        // generate files needed to plot the waveform using GTKWave
        $dumpfile("reg_wavedata.vcd");
		$dumpvars(0, reg_tb);
        
        // assign values with time to input signals to see output 
        RESET = 1'b0;
        WRITEENABLE = 1'b0;
        
        #1
        RESET = 1'b1;
        READREG1 = 3'd0;
        READREG2 = 3'd2;
        
        #8
        RESET = 1'b0;
        
        #5
        WRITEREG = 3'd2;
        WRITEDATA = 8'd76;
        WRITEENABLE = 1'b1;
        
        #10
        WRITEENABLE = 1'b0;
        
        #1
        READREG1 = 3'd2;
        
        #9
        WRITEREG = 3'd1;
        WRITEDATA = 8'd28;
        WRITEENABLE = 1'b1;
        READREG1 = 3'd1;
        
        #10
        WRITEENABLE = 1'b0;
        
        #10
        WRITEREG = 3'd4;
        WRITEDATA = 8'd6;
        WRITEENABLE = 1'b1;
		
		#9
        WRITEREG = 3'd1;
        WRITEDATA = 8'd35;
        WRITEENABLE = 1'b1;
        READREG2 = 3'd2;
        
        
        #10
        WRITEENABLE = 1'b0;
		
		READREG1 = 3'd1;
        
        #6
        WRITEREG = 3'd2;
        WRITEDATA = 8'd50;
        WRITEENABLE = 1'b1;
        
        #5
        WRITEENABLE = 1'b0;
        
        #10
        $finish;
    end
    
    // clock signal generation
    always
        #5 CLK = ~CLK;
        

endmodule

lab5/e16267_lab5_part2/reg_wavedata.vcd
$date
	Sat Sep 12 17:23:59 2020
$end
$version
	Icarus Verilog
$end
$timescale
	1s
$end
$scope module reg_tb $end
$var wire 8 ! REGOUT2 [7:0] $end
$var wire 8 " REGOUT1 [7:0] $end
$var reg 1 # CLK $end
$var reg 3 $ READREG1 [2:0] $end
$var reg 3 % READREG2 [2:0] $end
$var reg 1 & RESET $end
$var reg 8 ' WRITEDATA [7:0] $end
$var reg 1 ( WRITEENABLE $end
$var reg 3 ) WRITEREG [2:0] $end
$scope module myregfile $end
$var wire 1 # CLK $end
$var wire 8 * IN [7:0] $end
$var wire 3 + INADDRESS [2:0] $end
$var wire 8 , OUT1 [7:0] $end
$var wire 3 - OUT1ADDRESS [2:0] $end
$var wire 8 . OUT2 [7:0] $end
$var wire 3 / OUT2ADDRESS [2:0] $end
$var wire 1 & RESET $end
$var wire 1 ( WRITE $end
$var integer 32 0 i [31:0] $end
$upscope $end
$upscope $end
$enddefinitions $end
#0
$dumpvars
bx 0
bx /
bx .
bx -
bx ,
bx +
bx *
bx )
0(
bx '
0&
bx %
bx $
1#
bx "
bx !
$end
#1
b10 %
b10 /
b0 $
b0 -
1&
#3
b1000 0
#5
b0 !
b0 .
b0 "
b0 ,
0#
#9
0&
#10
1#
#14
1(
b1001100 '
b1001100 *
b10 )
b10 +
#15
0#
#20
1#
#24
b1001100 !
b1001100 .
0(
#25
b10 $
b10 -
0#
#27
b1001100 "
b1001100 ,
#30
1#
#34
b1 $
b1 -
1(
b11100 '
b11100 *
b1 )
b1 +
#35
0#
#36
b0 "
b0 ,
#40
1#
#44
b11100 "
b11100 ,
0(
#45
0#
#50
1#
#54
1(
b110 '
b110 *
b100 )
b100 +
#55
0#
#60
1#
#63
b100011 '
b100011 *
b1 )
b1 +
#65
0#
#70
1#
#73
0(
#74
b100011 "
b100011 ,
#75
0#
#79
1(
b110010 '
b110010 *
b10 )
b10 +
#80
1#
#84
b110010 !
b110010 .
0(
