lab5/New folder (3)/cpu.v
// Computer Architecture (CO224) - Lab 05
// Design: CPU of Simple Processor with beq and j insructions
// Author: E/16/267


/*ALU module */
module alu(DATA1,DATA2,RESULT,SELECT,ZERO);

input  [7:0] DATA1,DATA2;		// ALU  Inputs 
input  [2:0] SELECT;			// ALU Selection
output [7:0] RESULT;			// ALU 8-bit Output

output ZERO;
reg [7:0] RESULT;
//connect to nor gate
wire ZERO;			


//  to get raise zero flag when result==0 using multiple input nor gate
nor n1(ZERO,RESULT[0],RESULT[1],RESULT[2],RESULT[3],RESULT[4],RESULT[5],RESULT[6],RESULT[7]);

always @(DATA1,DATA2,SELECT)

	begin

	case(SELECT)
		3'b000: #1 RESULT = DATA2;			//FORWARD	
		3'b001: #2 RESULT = DATA1 + DATA2;	//ADD
		3'b010: #1 RESULT = DATA1 & DATA2;  //AND
		3'b011: #1 RESULT = DATA1 | DATA2;  //OR
		default:RESULT=8'bx;			    //RESERVED
	endcase
	end
	
endmodule


/* Register file module*/
module reg_file(IN, OUT1, OUT2, INADDRESS, OUT1ADDRESS, OUT2ADDRESS, WRITE, CLK, RESET);

//reg_file myregfile(WRITEDATA, REGOUT1, REGOUT2, WRITEREG, READREG1, READREG2, WRITEENABLE, CLK, RESET);

	input CLK,WRITE,RESET;
	input [2:0] INADDRESS,OUT1ADDRESS, OUT2ADDRESS;
	input [7:0] IN;
	output [7:0] OUT1, OUT2;
	
	reg [7:0] r[7:0]; //for assign to 7 registers
	integer i;

	assign #2 OUT1=r[OUT1ADDRESS];
	assign #2 OUT2=r[OUT2ADDRESS];
	
	//for reset=1 with level trigerring
	always @(RESET) 	
	begin
		if(RESET)
		#2   //timing delay
			for (i=0; i<8; i=i+1)   //making registers array
			begin
                r[i]=8'b00000000; 
			end
	end
	
	//for no reset && write with edge triggering
	always @(posedge CLK)
	begin
		if(!RESET && WRITE)
			begin
				#2 r[INADDRESS]=IN;  //assign writedata to registers
			end
	end
	
	
	
endmodule

//multiplexer for select Two's Complement and Immediate value in the control unit
module mux(OUT,SELECT,INPUT1,INPUT2);

	input SELECT,clk;
	input [7:0] INPUT1,INPUT2;
	output reg [7:0] OUT;

	always @* 
	begin
		if (SELECT==0)
		begin
			OUT = INPUT1;
		end
		else 
		begin
			OUT = INPUT2;
		end
	end
endmodule

//twos compliment module when sustractor is called
module twos_compliment(OUT,IN);

	input [7:0] IN;
	output [7:0] OUT;
	reg [7:0] OUT;

	always @(IN)
	begin
		OUT= ~IN + 8'b00000001; //getting compliment bitwise
	end
	
endmodule

//control unit for control muxes and opcode
//input = instruction opcode
//output = select for alu and input to muxes in the cpu module and beq and j signals

module control_unit(OPCODE,SELECT,MUX_IMMEDIATE,MUX_SIGNED,WRITE,J_SIGNAL,BEQ_SIGNAL);	//control unit
	input [7:0] OPCODE;
	output [2:0] SELECT;
	//control signal outputs
	output MUX_IMMEDIATE,MUX_SIGNED,WRITE,J_SIGNAL,BEQ_SIGNAL;
	reg MUX_IMMEDIATE,MUX_SIGNED,WRITE,J_SIGNAL,BEQ_SIGNAL;
	
	//delay #1 to decoding the instruction
	assign #1 SELECT = OPCODE [2:0]; //select should be OPCODEs last three bits for alu 
	
	always @(OPCODE) 
	begin
		case(OPCODE)		//add delay of #1 to opcode
			8'b00000000:
			#1	begin 	//for mov
			    WRITE=1'b1; 
				MUX_IMMEDIATE = 1'b1;
				MUX_SIGNED = 1'b0;
				BEQ_SIGNAL=1'b0;
				J_SIGNAL=1'b0;
				end
			8'b00000001:
			#1	begin 	//for add	
				WRITE=1'b1; 
				MUX_IMMEDIATE = 1'b1;
				MUX_SIGNED = 1'b0;
				BEQ_SIGNAL=1'b0;
				J_SIGNAL=1'b0;
				end
			8'b00001001:
			#1	begin 	//sub
				WRITE=1'b1; 
				MUX_IMMEDIATE = 1'b1;
				MUX_SIGNED = 1'b1;  //for get 2's compliement for sub
				J_SIGNAL=1'b0;
				BEQ_SIGNAL=1'b0;
				end
			8'b00000010:
			#1	begin 	//and	
				WRITE=1'b1; 
				MUX_IMMEDIATE = 1'b1;
				MUX_SIGNED = 1'b0;
				BEQ_SIGNAL=1'b0;
				J_SIGNAL=1'b0;
				end
			8'b00000011:
			#1	begin 	//or
				WRITE=1'b1; 
				MUX_IMMEDIATE = 1'b1;
				MUX_SIGNED = 1'b0;
				BEQ_SIGNAL=1'b0;
				J_SIGNAL=1'b0;
				end
			8'b00001000:
			#1	begin 	//for load	
				WRITE=1'b1; 
				MUX_IMMEDIATE = 1'b0;
				MUX_SIGNED = 1'b0;
				BEQ_SIGNAL=1'b0;
				J_SIGNAL=1'b0;
				end	
	        8'b00011001:
			#1	begin 	//for BEQ_SIGNAL FOR SUB where beq signal=1
				WRITE=1'b0; 
				MUX_IMMEDIATE = 1'b1;
				MUX_SIGNED = 1'b1; //check equality by subtracting
				BEQ_SIGNAL=1'b1;
				J_SIGNAL=1'b0;
				end
			8'b00000110:
			#1	begin 	//for J_SIGNAL	for jump instruction
				WRITE=1'b0; 
				MUX_IMMEDIATE = 1'b1;
				MUX_SIGNED = 1'b0;
				BEQ_SIGNAL=1'b0;
				J_SIGNAL=1'b1;
				end
			
		endcase
			
	end
endmodule



//dedicated adder for increment pc by 4
module adder(NUM1,NUM2,SUM);
    input[31:0] NUM1,NUM2;
	output [31:0] SUM;
	 
	assign  #2 SUM=NUM1 +NUM2; //increment by delay of 2 when adding 4 to pc
	
endmodule



//module for add pc for beq and j operations with sigend shitf value
module Add_ALU(PCout, ShiftOut, Add_ALUOut);

	input  [31:0] PCout;
	input signed [31:0] ShiftOut;
	
	output  reg [31:0] Add_ALUOut;

	always @(*) begin
		#2 Add_ALUOut = PCout + ShiftOut;
	end
endmodule


   
   
//module to Converts a 8-bit value to a sign-extended 32-bit value.
module Sign_Extender(in, out);

input wire [7:0] in; //in - a 8-bit signed integer.
output wire [31:0] out; //out - a 32-bit signed integer.

//replicate the sign bit of input into the high 8 bits of output.
assign out = {{8{in[7]}}, in[7:0]};

endmodule





//Shifts a 32-bit value left two places.
module Left_Shift(in, out);

input  wire signed [31:0] in;
output  wire signed[31:0] out;

//Output the shifted value.
//out -- A 32-bit integer that is equivalent to the input, but shifted left 2 places.

assign out = {in[29:0], 2'b0}; 


endmodule


//cpu module
//instruction decoding ,pc increment for happens here
module cpu(PC,INSTRUCTION,CLK,RESET);
	input [31:0] INSTRUCTION;
	input CLK,RESET;
	output reg [31:0] PC;
	
	wire WRITE;
	//zero flag output from alu
	wire ZERO; 
	//control signal od BEQ and j from control unit
	wire beq,j; 
	//control signal to 2's compliment and immediate operand in alu
	wire IMMEDIATE_SELECT,SUB_SELECT; 
	//outputs of AND and OR gates of incrementing pc for j,beq
	wire result_and,result_or;
	
	//for increment pc with given signal
	wire [31:0] PC_NEXT,PC_Sumbeq;
	
	//for module alu and register
	wire [2:0] ALUOP,SRC_2 ,SRC_1,WRITEREG;
	wire [7:0] OPCODE,Immediate,OUT1,OUT2,ALURESULT,twosComplement,muxSout,muxIout;
	
	//sign-extended module and left shift module inputs outputs
	wire signed [7:0] DESTINATION;
	wire signed [31:0] shift_offset,unshift_offset;
	
	
	
	
	//instruction decoding  
	assign  WRITEREG    = INSTRUCTION[18:16];
	assign  OPCODE 		= INSTRUCTION[31:24];
	assign  Immediate   = INSTRUCTION[7:0];
	assign  SRC_1       = INSTRUCTION[10:8];
	assign  SRC_2       = INSTRUCTION[2:0];
	assign DESTINATION  = INSTRUCTION[23:16]; //for sign extender
	
	
	
	//send current pc value to increment by 4
    adder PCadder(PC,4,PC_NEXT);
	//SEND INSTRUCTION[23:16] to sign extend
	Sign_Extender add(DESTINATION,unshift_offset);
	//shift unshif offset
	Left_Shift shift(unshift_offset,shift_offset);
	//send shift_offset to increment with current PC
	Add_ALU add_pcbeq(PC_NEXT,shift_offset,PC_Sumbeq);
	//send values to control unit
    control_unit mycu(OPCODE,ALUOP,IMMEDIATE_SELECT,SUB_SELECT,WRITE,j,beq);
	//reg_file
	reg_file regfile(ALURESULT,OUT1,OUT2,WRITEREG,SRC_1,SRC_2,WRITE,CLK,RESET);
	//twosComplement module to sustractor
	twos_compliment mytwos_compliment(twosComplement,OUT2);
	//mux for select sub or other operartions
	mux mulx_Sign(muxSout,SUB_SELECT,OUT2,twosComplement);  
	//mux for select load or other muxout
	mux mulx_Immediate(muxIout,IMMEDIATE_SELECT,Immediate,muxSout);
	//send final values to done alu operations
	alu myalu(OUT1,muxIout,ALURESULT,ALUOP,ZERO);
	
	
                      	
	//when reset
    always@(RESET)
	begin
	if(RESET)
	begin
	#1			//update with delay of #1
	PC =-32'd4;
	end
	end
	
	//for get ZERO =1'b1 && beq=1'b1
	and a2(result_and,ZERO, beq);
	//for get ZERO =1'b1 && beq=1'b1 || j=1'b1
	or or1(result_or,j, result_and);
	
	always@(posedge CLK)
	 
	begin
		if(RESET)
			begin
			#1			//update with delay of #1
			PC =-32'd4;
			end
		else if(result_or==1) //if result of or gate is 1 pc increment
			begin
			#1 PC = PC_Sumbeq;
			end
		else
			begin
				#1 
				PC=PC_NEXT;
			end
		
	end
	
	
	
	
endmodule

lab5/New folder (3)/CPU_TEST.v
// Computer Architecture (CO224) - Lab 05
// Design: Testbench of Integrated CPU of Simple Processor with beq and jump insructions
// Author: E/16/267

`include "cpu.v"

module cpu_tb;

    reg CLK, RESET;
    wire [31:0] PC;
    wire [31:0] INSTRUCTION;
    
	//Initialize an array of registers (8x1024) to be used as instruction memory
    reg [7:0] instr_mem[1023:0];
	
	//TODO: Create combinational logic to fetch an instruction from instruction memory, given the Program Counter(PC) value 
	assign #2 INSTRUCTION={instr_mem[PC+3], instr_mem[PC+2], instr_mem[PC+1], instr_mem[PC+0]};
    
    initial
    begin
        //Initialize instruction memory with a set of instructions
        
	
		
		    {instr_mem[10'd3], instr_mem[10'd2], instr_mem[10'd1], instr_mem[10'd0]}     = 32'b00001000000001100000000000001010;	// loadi 6 X 10
			{instr_mem[10'd7], instr_mem[10'd6], instr_mem[10'd5], instr_mem[10'd4]}     = 32'b00001000000001000000000000001111;	// loadi 4 X 15
			{instr_mem[10'd11], instr_mem[10'd10], instr_mem[10'd9], instr_mem[10'd8]}   = 32'b00001000000000110000000000001010;	// loadi 3 X 10
			{instr_mem[10'd15], instr_mem[10'd14], instr_mem[10'd13], instr_mem[10'd12]} = 32'b00000001000001010000011000000011;	// add  5 6 3
			{instr_mem[10'd19], instr_mem[10'd18], instr_mem[10'd17], instr_mem[10'd16]} = 32'b00011001000000100000011000000011;	// beq  2 6 3
			{instr_mem[10'd23], instr_mem[10'd22], instr_mem[10'd21], instr_mem[10'd20]} = 32'b00000001000001010000011000000011;	// add   5 6 3
			{instr_mem[10'd27], instr_mem[10'd26], instr_mem[10'd25], instr_mem[10'd24]} = 32'b00000011000001010000011000000011;	// or   5 6 3
			{instr_mem[10'd31], instr_mem[10'd30], instr_mem[10'd29], instr_mem[10'd28]} = 32'b00000000000001110000000000000011;    // mov   7 x 3 (beq)
			{instr_mem[10'd35], instr_mem[10'd34], instr_mem[10'd33], instr_mem[10'd32]} = 32'b00000110000000010000000000000001;	// j    1
			{instr_mem[10'd39], instr_mem[10'd38], instr_mem[10'd37], instr_mem[10'd36]} = 32'b00000010000000010000010000000101;    // and   1 4 5
			{instr_mem[10'd43], instr_mem[10'd42], instr_mem[10'd41], instr_mem[10'd40]} = 32'b00000001000001100000011100000100;    // add  6 7 4 (jump)
			{instr_mem[10'd47], instr_mem[10'd46], instr_mem[10'd45], instr_mem[10'd44]} = 32'b00001001000001000000011100000011;    // sub   4 7 3
			{instr_mem[10'd51], instr_mem[10'd50], instr_mem[10'd49], instr_mem[10'd48]} = 32'b00000001000001000000011100000011;    // add   4 7 3
			
			
			
			
			
	end
    
    /* 
    -----
     CPU
    -----
    */
    cpu mycpu(PC, INSTRUCTION, CLK, RESET);

    initial
    begin
    
        // generate files needed to plot the waveform using GTKWave
        $dumpfile("cpu_wavedata.vcd");
		$dumpvars(0, cpu_tb);
        
        CLK = 1'b0;
        RESET = 1'b0;
        
        // TODO: Reset the CPU (by giving a pulse to RESET signal) to start the program execution
		#3
		RESET = 1'b1;
		 
		#5
		RESET = 1'b0;
        
        // finish simulation after some time
        #150
        $finish;
        
    end
    
    // clock signal generation
    always
        #5 CLK = ~CLK;
        

endmodule

lab5/New folder (3)/cpu_wavedata.vcd
$date
	Sat Sep 12 17:25:51 2020
$end
$version
	Icarus Verilog
$end
$timescale
	1s
$end
$scope module cpu_tb $end
$var wire 32 ! PC [31:0] $end
$var wire 32 " INSTRUCTION [31:0] $end
$var reg 1 # CLK $end
$var reg 1 $ RESET $end
$scope module mycpu $end
$var wire 1 # CLK $end
$var wire 32 % INSTRUCTION [31:0] $end
$var wire 1 $ RESET $end
$var wire 1 & result_and $end
$var wire 1 ' result_or $end
$var wire 32 ( unshift_offset [31:0] $end
$var wire 8 ) twosComplement [7:0] $end
$var wire 32 * shift_offset [31:0] $end
$var wire 8 + muxSout [7:0] $end
$var wire 8 , muxIout [7:0] $end
$var wire 1 - j $end
$var wire 1 . beq $end
$var wire 1 / ZERO $end
$var wire 3 0 WRITEREG [2:0] $end
$var wire 1 1 WRITE $end
$var wire 1 2 SUB_SELECT $end
$var wire 3 3 SRC_2 [2:0] $end
$var wire 3 4 SRC_1 [2:0] $end
$var wire 32 5 PC_Sumbeq [31:0] $end
$var wire 32 6 PC_NEXT [31:0] $end
$var wire 8 7 OUT2 [7:0] $end
$var wire 8 8 OUT1 [7:0] $end
$var wire 8 9 OPCODE [7:0] $end
$var wire 8 : Immediate [7:0] $end
$var wire 1 ; IMMEDIATE_SELECT $end
$var wire 8 < DESTINATION [7:0] $end
$var wire 8 = ALURESULT [7:0] $end
$var wire 3 > ALUOP [2:0] $end
$var reg 32 ? PC [31:0] $end
$scope module PCadder $end
$var wire 32 @ NUM1 [31:0] $end
$var wire 32 A NUM2 [31:0] $end
$var wire 32 B SUM [31:0] $end
$upscope $end
$scope module add $end
$var wire 8 C in [7:0] $end
$var wire 32 D out [31:0] $end
$upscope $end
$scope module add_pcbeq $end
$var wire 32 E PCout [31:0] $end
$var wire 32 F ShiftOut [31:0] $end
$var reg 32 G Add_ALUOut [31:0] $end
$upscope $end
$scope module mulx_Immediate $end
$var wire 8 H INPUT1 [7:0] $end
$var wire 1 I clk $end
$var wire 1 ; SELECT $end
$var wire 8 J INPUT2 [7:0] $end
$var reg 8 K OUT [7:0] $end
$upscope $end
$scope module mulx_Sign $end
$var wire 1 L clk $end
$var wire 1 2 SELECT $end
$var wire 8 M INPUT2 [7:0] $end
$var wire 8 N INPUT1 [7:0] $end
$var reg 8 O OUT [7:0] $end
$upscope $end
$scope module myalu $end
$var wire 8 P DATA2 [7:0] $end
$var wire 1 / ZERO $end
$var wire 3 Q SELECT [2:0] $end
$var wire 8 R DATA1 [7:0] $end
$var reg 8 S RESULT [7:0] $end
$upscope $end
$scope module mycu $end
$var wire 8 T OPCODE [7:0] $end
$var wire 3 U SELECT [2:0] $end
$var reg 1 . BEQ_SIGNAL $end
$var reg 1 - J_SIGNAL $end
$var reg 1 ; MUX_IMMEDIATE $end
$var reg 1 2 MUX_SIGNED $end
$var reg 1 1 WRITE $end
$upscope $end
$scope module mytwos_compliment $end
$var wire 8 V IN [7:0] $end
$var reg 8 W OUT [7:0] $end
$upscope $end
$scope module regfile $end
$var wire 1 # CLK $end
$var wire 8 X IN [7:0] $end
$var wire 3 Y INADDRESS [2:0] $end
$var wire 8 Z OUT1 [7:0] $end
$var wire 3 [ OUT1ADDRESS [2:0] $end
$var wire 8 \ OUT2 [7:0] $end
$var wire 3 ] OUT2ADDRESS [2:0] $end
$var wire 1 $ RESET $end
$var wire 1 1 WRITE $end
$var integer 32 ^ i [31:0] $end
$upscope $end
$scope module shift $end
$var wire 32 _ in [31:0] $end
$var wire 32 ` out [31:0] $end
$upscope $end
$upscope $end
$upscope $end
$enddefinitions $end
#0
$dumpvars
b0xxxxxxxxxxxxxxxx00 `
b0xxxxxxxxxxxxxxxx _
bx ^
bx ]
bx \
bx [
bx Z
bx Y
bx X
bx W
bx V
bx U
bx T
bx S
bx R
bx Q
bx P
bx O
bx N
bx M
zL
bx K
bx J
zI
bx H
bx G
b0xxxxxxxxxxxxxxxx00 F
bx E
b0xxxxxxxxxxxxxxxx D
bx C
bx B
b100 A
bx @
bx ?
bx >
bx =
bx <
x;
bx :
bx 9
bx 8
bx 7
bx 6
bx 5
bx 4
bx 3
x2
x1
bx 0
x/
x.
x-
bx ,
bx +
b0xxxxxxxxxxxxxxxx00 *
bx )
b0xxxxxxxxxxxxxxxx (
x'
x&
bx %
0$
0#
bx "
bx !
$end
#3
1$
#4
b11111111111111111111111111111100 !
b11111111111111111111111111111100 ?
b11111111111111111111111111111100 @
#5
b1000 ^
1#
#6
b0 6
b0 B
b0 E
#8
0$
#10
0#
#15
1#
#16
b0 !
b0 ?
b0 @
#18
b11000 *
b11000 F
b11000 `
b110 0
b110 Y
b1000 9
b1000 T
b1010 :
b1010 H
b0 4
b0 [
b10 3
b10 ]
b110 (
b110 D
b110 _
b110 <
b110 C
b100 6
b100 B
b100 E
b1000000001100000000000001010 "
b1000000001100000000000001010 %
#19
0'
0&
b1010 ,
b1010 K
b1010 P
0-
0.
02
0;
11
b0 >
b0 Q
b0 U
#20
0/
b0 +
b0 J
b0 O
b0 )
b0 M
b0 W
b1010 =
b1010 S
b1010 X
b11100 5
b11100 G
b0 8
b0 R
b0 Z
b0 7
b0 N
b0 V
b0 \
0#
#25
1#
#26
b100 !
b100 ?
b100 @
#28
b1111 ,
b1111 K
b1111 P
b10000 *
b10000 F
b10000 `
b100 0
b100 Y
b1111 :
b1111 H
b111 3
b111 ]
b100 (
b100 D
b100 _
b100 <
b100 C
b1000 6
b1000 B
b1000 E
b1000000001000000000000001111 "
b1000000001000000000000001111 %
#29
b1111 =
b1111 S
b1111 X
#30
b11000 5
b11000 G
0#
#35
1#
#36
b1000 !
b1000 ?
b1000 @
#38
b1010 ,
b1010 K
b1010 P
b1100 *
b1100 F
b1100 `
b11 0
b11 Y
b1010 :
b1010 H
b10 3
b10 ]
b11 (
b11 D
b11 _
b11 <
b11 C
b1100 6
b1100 B
b1100 E
b1000000000110000000000001010 "
b1000000000110000000000001010 %
#39
b1010 =
b1010 S
b1010 X
#40
0#
#45
1#
#46
b1100 !
b1100 ?
b1100 @
#48
b11 ,
b11 K
b11 P
b10100 *
b10100 F
b10100 `
b101 0
b101 Y
b1 9
b1 T
b11 :
b11 H
b110 4
b110 [
b11 3
b11 ]
b101 (
b101 D
b101 _
b101 <
b101 C
b10000 6
b10000 B
b10000 E
b1000001010000011000000011 "
b1000001010000011000000011 %
#49
b0 ,
b0 K
b0 P
b11 =
b11 S
b11 X
1;
b1 >
b1 Q
b1 U
#50
b1010 ,
b1010 K
b1010 P
b1010 +
b1010 J
b1010 O
b11110110 )
b11110110 M
b11110110 W
b100100 5
b100100 G
b1010 8
b1010 R
b1010 Z
b1010 7
b1010 N
b1010 V
b1010 \
0#
#51
b10100 =
b10100 S
b10100 X
#55
1#
#56
b10000 !
b10000 ?
b10000 @
#58
b1000 *
b1000 F
b1000 `
b10 0
b10 Y
b11001 9
b11001 T
b10 (
b10 D
b10 _
b10 <
b10 C
b10100 6
b10100 B
b10100 E
b11001000000100000011000000011 "
b11001000000100000011000000011 %
#59
b11110110 ,
b11110110 K
b11110110 P
b11110110 +
b11110110 J
b11110110 O
1.
12
01
#60
b11100 5
b11100 G
0#
#61
1'
1&
1/
b0 =
b0 S
b0 X
#65
1#
#66
b11100 !
b11100 ?
b11100 @
#68
b11100 *
b11100 F
b11100 `
b111 0
b111 Y
b0 9
b0 T
b0 4
b0 [
b111 (
b111 D
b111 _
b111 <
b111 C
b100000 6
b100000 B
b100000 E
b1110000000000000011 "
b1110000000000000011 %
#69
0'
b1010 ,
b1010 K
b1010 P
0&
b1010 +
b1010 J
b1010 O
0.
02
11
b0 >
b0 Q
b0 U
#70
0/
b1010 =
b1010 S
b1010 X
b111100 5
b111100 G
b0 8
b0 R
b0 Z
0#
#75
1#
#76
b100000 !
b100000 ?
b100000 @
#78
b100 *
b100 F
b100 `
b1 0
b1 Y
b110 9
b110 T
b1 :
b1 H
b1 3
b1 ]
b1 (
b1 D
b1 _
b1 <
b1 C
b100100 6
b100100 B
b100100 E
b110000000010000000000000001 "
b110000000010000000000000001 %
#79
x/
1'
bx =
bx S
bx X
1-
01
b110 >
b110 Q
b110 U
#80
b0 ,
b0 K
b0 P
b0 +
b0 J
b0 O
b0 )
b0 M
b0 W
b101000 5
b101000 G
b0 7
b0 N
b0 V
b0 \
0#
#85
1#
#86
b101000 !
b101000 ?
b101000 @
#88
b11000 *
b11000 F
b11000 `
b110 0
b110 Y
b1 9
b1 T
b100 :
b100 H
b111 4
b111 [
b100 3
b100 ]
b110 (
b110 D
b110 _
b110 <
b110 C
b101100 6
b101100 B
b101100 E
b1000001100000011100000100 "
b1000001100000011100000100 %
#89
0'
0-
11
b1 >
b1 Q
b1 U
#90
b1111 ,
b1111 K
b1111 P
b1111 +
b1111 J
b1111 O
b11110001 )
b11110001 M
b11110001 W
b1000100 5
b1000100 G
b1010 8
b1010 R
b1010 Z
b1111 7
b1111 N
b1111 V
b1111 \
0#
#91
0/
b11001 =
b11001 S
b11001 X
#95
1#
#96
b101100 !
b101100 ?
b101100 @
#98
b10000 *
b10000 F
b10000 `
b100 0
b100 Y
b1001 9
b1001 T
b11 :
b11 H
b11 3
b11 ]
b100 (
b100 D
b100 _
b100 <
b100 C
b110000 6
b110000 B
b110000 E
b1001000001000000011100000011 "
b1001000001000000011100000011 %
#99
b11110001 ,
b11110001 K
b11110001 P
b11110001 +
b11110001 J
b11110001 O
12
#100
b11110110 ,
b11110110 K
b11110110 P
b11110110 +
b11110110 J
b11110110 O
b11110110 )
b11110110 M
b11110110 W
b1000000 5
b1000000 G
b1010 7
b1010 N
b1010 V
b1010 \
0#
#101
1/
b0 =
b0 S
b0 X
#105
1#
#106
b110000 !
b110000 ?
b110000 @
#108
b1 9
b1 T
b110100 6
b110100 B
b110100 E
b1000001000000011100000011 "
b1000001000000011100000011 %
#109
b1010 ,
b1010 K
b1010 P
b1010 +
b1010 J
b1010 O
02
#110
b1000100 5
b1000100 G
0#
#111
0/
b10100 =
b10100 S
b10100 X
#115
1#
#116
b110100 !
b110100 ?
b110100 @
#118
b0xxxxxxxxxxxxxxxx00 *
b0xxxxxxxxxxxxxxxx00 F
b0xxxxxxxxxxxxxxxx00 `
bx 0
bx Y
bx 9
bx T
bx :
bx H
bx 4
bx [
bx 3
bx ]
b0xxxxxxxxxxxxxxxx (
b0xxxxxxxxxxxxxxxx D
b0xxxxxxxxxxxxxxxx _
bx <
bx C
b111000 6
b111000 B
b111000 E
bx "
bx %
#119
x/
bx =
bx S
bx X
bx >
bx Q
bx U
#120
bx ,
bx K
bx P
bx +
bx J
bx O
bx )
bx M
bx W
bx 5
bx G
bx 8
bx R
bx Z
bx 7
bx N
bx V
bx \
0#
#125
1#
#126
b111000 !
b111000 ?
b111000 @
#128
b111100 6
b111100 B
b111100 E
#130
0#
#135
1#
#136
b111100 !
b111100 ?
b111100 @
#138
b1000000 6
b1000000 B
b1000000 E
#140
0#
#145
1#
#146
b1000000 !
b1000000 ?
b1000000 @
#148
b1000100 6
b1000100 B
b1000100 E
#150
0#
#155
1#
#156
b1000100 !
b1000100 ?
b1000100 @
#158
b1001000 6
b1001000 B
b1001000 E
